<?xml version="1.0" encoding="utf-8"?>
<extension version="3.9" type="library">
	<name>JT | Libraries metapackage</name>
	<version>1.0.0</version>
	<creationDate>31-may-2021</creationDate>
	<author>JTotal</author>
	<authorEmail>support@jtotal.org</authorEmail>
	<authorUrl>https://jtotal.org</authorUrl>
	<copyright>Copyright © 2021 JTotal - All Rights Reserved</copyright>
	<license>http://www.gnu.org/licenses/gpl-2.0.html GNU/GPL</license>
	<libraryname>jtlibs</libraryname>

	<files>
		<file>jtlibs.xml</file>
	</files>

	<updateservers>
        <server type="extension" priority="1" name="JT Libraries updater">https://users.jtotal.org/SOFT/UPDATES/FRAMEWORK/JTLibs/jtlibs-update.xml</server>
    </updateservers>

</extension>
